generalized_contrastive_PCA/__init__.py
generalized_contrastive_PCA/contrastive_methods.py
generalized_contrastive_pca-1.0.2.dist-info/licenses/LICENSE
generalized_contrastive_pca-1.0.2.dist-info/METADATA
generalized_contrastive_pca-1.0.2.dist-info/WHEEL
generalized_contrastive_pca-1.0.2.dist-info/top_level.txt
generalized_contrastive_pca-1.0.2.dist-info/RECORD
